axon_api/__init__.py
axon_api/core/__init__.py
axon_api/core/application.py
axon_api/core/errors.py
axon_api/core/headers.py
axon_api/core/mimetype.py
axon_api/core/response.py
axon_api/core/sanitizer.py
axon_api/core/streaming.py
axon_api/services/__init__.py
axon_api/services/logger.py
axon_api-0.9.0.dist-info/METADATA
axon_api-0.9.0.dist-info/WHEEL
axon_api-0.9.0.dist-info/top_level.txt
axon_api-0.9.0.dist-info/RECORD
