Metadata-Version: 2.4
Name: axon-api
Version: 0.9.0
Summary: Zero-dependency WSGI framework with request batching, multipart streaming, and HTTP range support. Built for applications that require high performance without the bloat.
Home-page: https://github.com/b-is-for-build/axon-api
Author: B LLC
Author-email: b-is-for-build@bellone.com
License: MIT
Project-URL: Bug Reports, https://github.com/b-is-for-build/axon-api/issues
Project-URL: Source, https://github.com/b-is-for-build/axon-api
Project-URL: Documentation, https://github.com/b-is-for-build/axon-api#readme
Keywords: wsgi framework streaming multipart http-range zero-dependency
Classifier: Development Status :: 4 - Beta
Classifier: Intended Audience :: Developers
Classifier: Operating System :: OS Independent
Classifier: Programming Language :: Python :: 3.10
Classifier: Programming Language :: Python :: 3.11
Classifier: Programming Language :: Python :: 3.12
Classifier: Programming Language :: Python :: 3.13
Classifier: Topic :: Internet :: WWW/HTTP :: WSGI
Classifier: Topic :: Internet :: WWW/HTTP :: WSGI :: Server
Classifier: Topic :: Software Development :: Libraries :: Python Modules
Requires-Python: >=3.10
Dynamic: author
Dynamic: author-email
Dynamic: classifier
Dynamic: description
Dynamic: description-content-type
Dynamic: home-page
Dynamic: keywords
Dynamic: license
Dynamic: project-url
Dynamic: requires-python
Dynamic: summary
